nand2adder/full_adder_nand.v
module full_adder_nand (
    input  A,
    input  B,
    input  Cin,
    output S,
    output Cout
);

    wire w1, w2, w3, w4, w5, w6, w7;

    //harf adder
    nand g1 (w1, A, B);
    nand g2 (w2, A, w1);
    nand g3 (w3, B, w1);
    nand g4 (w4, w2, w3);

    //harf adder
    nand g5 (w5, w4, Cin);
    nand g6 (w6, w4, w5);
    nand g7 (w7, Cin, w5);
    nand g8 (S, w6, w7);

    //carry
    nand g9 (Cout, w1, w5);

endmodule

nand2adder/tb_full_adder_nand.v

module tb_full_adder_nand;

    reg A, B, Cin;
    wire S, Cout;

    full_adder_nand adder (
        .A(A),
        .B(B),
        .Cin(Cin),
        .S(S),
        .Cout(Cout)
    );

    initial begin
        // $dumpfile("tb_full_adder_nand.vcd");
        $dumpvars(0, tb_full_adder_nand);
    end

    initial begin
        A = 0; B = 0; Cin = 0; #1;
        A = 0; B = 0; Cin = 1; #1;
        A = 0; B = 1; Cin = 0; #1;
        A = 0; B = 1; Cin = 1; #1;
        A = 1; B = 0; Cin = 0; #1;
        A = 1; B = 0; Cin = 1; #1;
        A = 1; B = 1; Cin = 0; #1;
        A = 1; B = 1; Cin = 1; #1;

        $finish;
    end
    
    initial begin
        $monitor("A=%b B=%b Cin=%b -> Cout=%b, S=%b",
                A, B, Cin, Cout, S);
    end

endmodule

nand2adder/dump.vcd
$date
	Wed May  7 16:54:26 2025
$end
$version
	Icarus Verilog
$end
$timescale
	1s
$end
$scope module tb_full_adder_nand $end
$var wire 1 ! S $end
$var wire 1 " Cout $end
$var reg 1 # A $end
$var reg 1 $ B $end
$var reg 1 % Cin $end
$scope module adder $end
$var wire 1 # A $end
$var wire 1 $ B $end
$var wire 1 % Cin $end
$var wire 1 " Cout $end
$var wire 1 ! S $end
$var wire 1 & w1 $end
$var wire 1 ' w2 $end
$var wire 1 ( w3 $end
$var wire 1 ) w4 $end
$var wire 1 * w5 $end
$var wire 1 + w6 $end
$var wire 1 , w7 $end
$upscope $end
$upscope $end
$enddefinitions $end
$comment Show the parameter values. $end
$dumpall
$end
#0
$dumpvars
1,
1+
1*
0)
1(
1'
1&
0%
0$
0#
0"
0!
$end
#1
1!
0,
1%
#2
0+
1!
1)
1,
0(
0%
1$
#3
0!
1+
1"
0*
1,
1%
#4
1!
0+
0"
1*
1(
0'
0%
0$
1#
#5
0!
1+
1"
0*
1,
1%
#6
0!
0)
1+
1'
1*
0&
1(
0%
1$
#7
1!
0,
1%
